spotify_playlist_tool/__init__.py
spotify_playlist_tool/__main__.py
spotify_playlist_tool/tool.py
spotify_playlist_tool-0.1.0.dist-info/METADATA
spotify_playlist_tool-0.1.0.dist-info/WHEEL
spotify_playlist_tool-0.1.0.dist-info/entry_points.txt
spotify_playlist_tool-0.1.0.dist-info/top_level.txt
spotify_playlist_tool-0.1.0.dist-info/RECORD
