Metadata-Version: 2.4
Name: spotify_playlist_tool
Version: 0.1.0
Summary: A CLI tool for managing Spotify playlists.
Author: Gretchen Maculo
License: MIT
Requires-Python: >=3.7
Requires-Dist: spotipy
Dynamic: author
Dynamic: description
Dynamic: description-content-type
Dynamic: license
Dynamic: requires-dist
Dynamic: requires-python
Dynamic: summary
